zdaemon/README.rst
zdaemon/__init__.py
zdaemon/__main__.py
zdaemon/component.xml
zdaemon/sample.conf
zdaemon/schema.xml
zdaemon/zdctl.py
zdaemon/zdoptions.py
zdaemon/zdrun.py
zdaemon/tests/__init__.py
zdaemon/tests/nokill.py
zdaemon/tests/parent.py
zdaemon/tests/tests.py
zdaemon/tests/testuser.py
zdaemon/tests/testzdctl.py
zdaemon/tests/testzdoptions.py
zdaemon/tests/testzdrun.py
zdaemon-5.1.dist-info/LICENSE.txt
zdaemon-5.1.dist-info/METADATA
zdaemon-5.1.dist-info/WHEEL
zdaemon-5.1.dist-info/entry_points.txt
zdaemon-5.1.dist-info/top_level.txt
zdaemon-5.1.dist-info/RECORD
